.travis.yml
README.rst
bootstrap.py
buildout.cfg
setup.py
validation-files.yaml
validation-options.yaml
docs/AUTHORS.rst
docs/HISTORY.rst
docs/LICENSE.rst
docs/api.rst
docs/conf.py
docs/conventions.rst
docs/env.rst
docs/index.rst
docs/release.rst
src/tbs/__init__.py
src/tbs/exceptions.py
src/tbs/tests/__init__.py
src/tbs/tests/test_tbs.py
src/thebestspinner.egg-info/PKG-INFO
src/thebestspinner.egg-info/SOURCES.txt
src/thebestspinner.egg-info/dependency_links.txt
src/thebestspinner.egg-info/not-zip-safe
src/thebestspinner.egg-info/requires.txt
src/thebestspinner.egg-info/top_level.txt