Metadata-Version: 1.1
Name: thebestspinner
Version: 1.0.2
Summary: Python bindings for TheBestSpinner API
Home-page: http://www.niteoweb.com
Author: NiteoWeb Ltd.
Author-email: info@niteoweb.com
License: MIT
Keywords: API spinner TheBestSpinner
Platform: UNKNOWN
Classifier: Programming Language :: Python
Classifier: Topic :: Internet :: WWW/HTTP
